ChatBattery/LLM_agent.py
ChatBattery/__init__.py
ChatBattery/decision_agent.py
ChatBattery/domain_agent.py
ChatBattery/rank_agent.py
ChatBattery/retrieval_agent.py
ChatBattery/search_agent.py
chatbattery-0.1.0.dist-info/licenses/LICENSE
chatbattery-0.1.0.dist-info/METADATA
chatbattery-0.1.0.dist-info/WHEEL
chatbattery-0.1.0.dist-info/top_level.txt
chatbattery-0.1.0.dist-info/RECORD
