Metadata-Version: 2.4
Name: ChatBattery
Version: 0.1.0
Summary: Add your description here
Author: Shengchao Liu
Requires-Python: >=3.10
License-File: LICENSE
Requires-Dist: ase>=3.26.0
Requires-Dist: flask>=3.1.2
Requires-Dist: levenshtein>=0.27.1
Requires-Dist: mcp[cli]>=1.13.1
Requires-Dist: mp-api==0.41.2
Requires-Dist: openai==0.28
Requires-Dist: pandas>=2.3.2
Requires-Dist: pymatgen==2024.4.13
Requires-Dist: scikit-learn>=1.7.2
Requires-Dist: xgboost>=3.0.5
Dynamic: author
Dynamic: license-file
